odoo/addons/product_supplierinfo_for_customer_invoice/README.rst
odoo/addons/product_supplierinfo_for_customer_invoice/__init__.py
odoo/addons/product_supplierinfo_for_customer_invoice/__manifest__.py
odoo/addons/product_supplierinfo_for_customer_invoice/i18n/it.po
odoo/addons/product_supplierinfo_for_customer_invoice/i18n/product_supplierinfo_for_customer_invoice.pot
odoo/addons/product_supplierinfo_for_customer_invoice/models/__init__.py
odoo/addons/product_supplierinfo_for_customer_invoice/models/account_invoice.py
odoo/addons/product_supplierinfo_for_customer_invoice/static/description/icon.png
odoo/addons/product_supplierinfo_for_customer_invoice/views/account_invoice_view.xml
odoo11_addon_product_supplierinfo_for_customer_invoice-11.0.1.0.0.99.dev4.dist-info/METADATA
odoo11_addon_product_supplierinfo_for_customer_invoice-11.0.1.0.0.99.dev4.dist-info/WHEEL
odoo11_addon_product_supplierinfo_for_customer_invoice-11.0.1.0.0.99.dev4.dist-info/top_level.txt
odoo11_addon_product_supplierinfo_for_customer_invoice-11.0.1.0.0.99.dev4.dist-info/RECORD
